[
  {
    "text": "ุจุงูุงุฎุฑู ุจุง ุฑูุดโ ูุฑุณูู ุฌุง ูููุด ุฏุงุฏู ๐\nุงูุฑฺโุชูู ุฑู ุจูุฑุณุชุฏโฆ ๐๐ฅ",
    "date": 1767815786,
    "link": "https://t.me/sinavm/4737"
  },
  {
    "text": "ฺฉุงููฺฏ ุงูุฑฺุงูุณ ููุชุฑุดฺฉูNV ๐ \n\nยยยยยย ๐จูู ุดฺฉู ู ุถุฏููุชุฑ๐จ\n\nูุตุจ:๐ ุงูุฏุฑูุฏยย ๐ฑ ุขููู\n\n๐ุจุง Boost ฺฉุฑุฏู (ุญูุงุช)ฺฉูุฏ\n#napsternetv #npvย\nโโโโโโโโ\n๐ ๐ช๐๐๐๐๐๐: @SINAVM๐",
    "date": 1767802546,
    "link": "https://t.me/sinavm/4736"
  },
  {
    "text": "ุนุดูุงุงุง.... \nููุฑ ฺุดูุงุงุง...\nูุนุงู ุดุฏ๐ค\nู ุชุณุชููู ูุดู...\nุจูฺ ุจูฺ ๐บ๐ผ๐\nุจุฏูู vpn ู ุจุง vpn ูุฑู ูุฏุงุฑู \nุจุฑุฏ ุชู ฺฏูฺฏู sinavm ุฑู ุณุฑฺ ฺฉูุฏ \nููููุฌุง ฺฉู ูุฑุฏ ุณุฑฺ ูฺฉูุฏ\nูุซู ุนฺฉุณ ุจุงูุง ุฑู ุจุฒูุฏ\n\nููุท ูุจูุด ุงูพ ุณูฺฏ ุจุงฺฉุณ ูุตุจ ุดุฏู ุจุงุดู\nฺฉุงููฺฏ ุจุง ุงููุฌ ๐ ฺฏุฐุงุดุชู\n#engine #sinavm",
    "date": 1767730014,
    "link": "https://t.me/sinavm/4732"
  },
  {
    "text": "โ ุฏุฑุฎูุงุณุช ูุง ุชูุณุท ฺฏูฺฏู ุชุฃุฏ ุดุฏ\n\nุขุฑูุ ุฏุฑุณุช ุฎููุฏ ๐\nฺฉุงููฺฏโูุง ู ุฏุณุชุฑุณโูุง SiNAVM ุชูุณุท\n ฺฏูฺฏู ุชุฃุฏ ุดุฏู ู ุงูุฏฺฉุณ ฺฉุงูู ฺฏุฑูุชู.\nูุจูุงู ฺฏูุชู ุงฺฏุฑ ูุช ูู ุดุฏ ู ุญุช ฺฏูฺฏู ูู ุจุณุชู ุจูุฏ ฺ ฺฉุงุฑ ฺฉูุฏุ\nุงูู ูุงุณู ุณูุงุฑู ุฎูฺฏ ูุทูู ุจูุฏ ๐\n\nุงูุง ุญุงูุง ุจุฑู ุณุฑุงุบ ุณูุงุฑู ุจุนุฏ ๐\nุนู ุงฺฏุฑ ูุช ูู ุดุฏ ูู ฺฏูฺฏู ุจุงุฒ ุจูุฏ\nูุซู ุจุนุฏ ุงุฒ ููุชูู ุฑูุฒ ุฌูฺฏ:\n๐ ููุท ฺฉุงูู ุชู ุงูุชุฑูุช (ูุฑูุฑฺฏุฑุชูู)ุณุฑฺ ฺฉูุฏ:\nsinavm\n๐ ุญุงูุง ุงู ุตูุญู ุฑู ุงูุชุฎุงุจ ฺฉูุฏ ๐\nSiNAVM | ุงุชุตุงู ููุดููุฏ\n\nโก ู ุจูู! ุงุชุตุงู ูุณุชูู ุจู Sing-box\nุจุฏูู ุชูฺฏุฑุงู ุ ุจุฏูู ฺฉุงูุงู ุ ุจุฏูู ููฺฉโ ู ูุงู\nุงู ุนู:\nโข ุชุฃุฏ ูุณุฑ ุชูุณุท ฺฏูฺฏู\nโข ุฏุณุชุฑุณ ุญุช ุชู ุดุฑุงุท ูููโุฎูู ๐\nโข ู ูพู ุงูู ููุช ุฑุงูโูุง ุจุณุชูโุงู\nุงู ุณุณุชู ุฏููุงู ุจุฑุง ููู ุฑูุฒุง ุณุงุฎุชู ุดุฏู\nุฑุงู ุณุงุฏูุ ููุช ุงูุถุงุน ูพฺุฏูโุณุช.\nููุดูุ ูุฏู ุงููุช ู ุฏุณุชุฑุณ ุจูุชุฑ ุดูุง ุจูุฏู ๐ค",
    "date": 1767647952,
    "link": "https://t.me/sinavm/4730"
  },
  {
    "text": "ุฒุญูุช ุงูุฑฺ ุจุง ุดูุง ๐จโ๐ป",
    "date": 1767607354,
    "link": "https://t.me/sinavm/4729"
  }
]